LICENSE
MANIFEST.in
README.md
pyproject.toml
setup.py
shorter_py.egg-info/PKG-INFO
shorter_py.egg-info/SOURCES.txt
shorter_py.egg-info/dependency_links.txt
shorter_py.egg-info/requires.txt
shorter_py.egg-info/top_level.txt
shorterpy/__init__.py
shorterpy/api/__init__.py
shorterpy/api/apiProvider.py
shorterpy/common/__init__.py
shorterpy/common/types.py
shorterpy/contracts/__init__.py
shorterpy/contracts/auctionHall.py
shorterpy/contracts/base.py
shorterpy/contracts/committee.py
shorterpy/contracts/constants.py
shorterpy/contracts/erc20.py
shorterpy/contracts/farming.py
shorterpy/contracts/poolGuardian.py
shorterpy/contracts/strPool.py
shorterpy/contracts/tradingHub.py
shorterpy/contracts/types.py
shorterpy/contracts/utils.py
shorterpy/contracts/vaultButler.py
shorterpy/contracts/abi/IAuctionHall.json
shorterpy/contracts/abi/ICommittee.json
shorterpy/contracts/abi/IERC20.json
shorterpy/contracts/abi/IFarming.json
shorterpy/contracts/abi/IPoolGuardian.json
shorterpy/contracts/abi/IStrPool.json
shorterpy/contracts/abi/ITradingHub.json
shorterpy/contracts/abi/IVaultButler.json