Metadata-Version: 2.1
Name: shorter-py
Version: 0.1.0
Summary: A Python library for interacting with the Shorter protocol
Home-page: https://github.com/DeveloperInProgress/ShorterPy
Author: Naveen Veluswamy
Author-email: velnaveen99@gmail.com
License: MIT
Keywords: ethereum,blockchain,shorter,contract,python
Platform: UNKNOWN
Classifier: Development Status :: 3 - Alpha
Classifier: Intended Audience :: Developers
Classifier: Topic :: Software Development :: Build Tools
Classifier: License :: OSI Approved :: MIT License
Classifier: Programming Language :: Python :: 3
Classifier: Programming Language :: Python :: 3.4
Classifier: Programming Language :: Python :: 3.5
Classifier: Programming Language :: Python :: 3.6
Classifier: Programming Language :: Python :: 3.7
Classifier: Programming Language :: Python :: 3.8
Classifier: Programming Language :: Python :: 3.9
License-File: LICENSE
